{
    "data_name":        "ldc_15k",

    "latent_type":      "pod",

    "latent_params": {
        "patch_size":   0,
        "num_modes":    200
    },

    "model":            "tr_enc",

    "params": {
        "time_lag":     64,
        "d_model":      512,
        "nhead":        4,
        "num_layers":   4,
        "embed":        "lin"
    },

    "train": {
        "train_split":  0.7,
        "test_split":   0.1,
        "sample_train": 0,
        "sample_test":  0,
        "lr":           0.001,
        "num_epochs":   1000,
        "patience":     25,
        "train_ahead":  1,
        "batch_size":   256
    },

    "predictions": {
        "validation": {
            "init":     "val",
            "lim":      null
        },
        "seen": {
            "init":     "train",
            "lim":      null
        },
        "long":
        {
            "init":     "val",
            "lim":      15000,
            "arg":      "extrap"
        }
    }
}
